[
  {
    "isin": "PL11BTS00015",
    "mbank_name": "11BIT",
    "full_name": "11 BIT STUDIOS SA",
    "figi_ticker": "11B",
    "exchange_code": "PW",
    "security_type": "Common Stock",
    "market_sector": "Equity",
    "figi": "BBG0018708N0",
    "source": "openfigi"
  },
  {
    "isin": "PLAB00000019",
    "mbank_name": "ABPL",
    "full_name": "AB SA",
    "figi_ticker": "ABE",
    "exchange_code": "PW",
    "security_type": "Common Stock",
    "market_sector": "Equity",
    "figi": "BBG000D2ZHY7",
    "source": "openfigi"
  },
  {
    "isin": "PLAGORA00067",
    "mbank_name": "AGORA",
    "full_name": "AGORA SA",
    "figi_ticker": "AGO",
    "exchange_code": "PW",
    "security_type": "Common Stock",
    "market_sector": "Equity",
    "figi": "BBG000F745M7",
    "source": "openfigi"
  },
  {
    "isin": "PLALIOR00045",
    "mbank_name": "ALIOR",
    "full_name": "ALIOR BANK SA",
    "figi_ticker": "ALR",
    "exchange_code": "PW",
    "security_type": "Common Stock",
    "market_sector": "Equity",
    "figi": "BBG003M95W30",
    "source": "openfigi"
  },
  {
    "isin": "LU2237380790",
    "mbank_name": "ALLEGRO",
    "full_name": "ALLEGRO.EU SA",
    "figi_ticker": "ALE",
    "exchange_code": "PW",
    "security_type": "Common Stock",
    "market_sector": "Equity",
    "figi": "BBG00XC93616",
    "source": "openfigi"
  },
  {
    "isin": "PLAMICA00010",
    "mbank_name": "AMICA",
    "full_name": "AMICA SA",
    "figi_ticker": "AMC",
    "exchange_code": "PW",
    "security_type": "Common Stock",
    "market_sector": "Equity",
    "figi": "BBG000CJ7SW0",
    "source": "openfigi"
  },
  {
    "isin": "ES0105375002",
    "mbank_name": "AMREST",
    "full_name": "AMREST HOLDINGS SE",
    "figi_ticker": "EAT",
    "exchange_code": "PW",
    "security_type": "Common Stock",
    "market_sector": "Equity",
    "figi": "BBG000BXN1R7",
    "source": "openfigi"
  },
  {
    "isin": "PLANSWR00019",
    "mbank_name": "ANSWEAR",
    "full_name": "ANSWEAR.COM SA - A",
    "figi_ticker": "ANR",
    "exchange_code": "PW",
    "security_type": "Common Stock",
    "market_sector": "Equity",
    "figi": "BBG00YT5MV90",
    "source": "openfigi"
  },
  {
    "isin": "PLAPATR00018",
    "mbank_name": "APATOR",
    "full_name": "APATOR SA",
    "figi_ticker": "APT",
    "exchange_code": "PW",
    "security_type": "Common Stock",
    "market_sector": "Equity",
    "figi": "BBG000CJ2519",
    "source": "openfigi"
  },
  {
    "isin": "PLARTPR00012",
    "mbank_name": "ARCTIC",
    "full_name": "ARCTIC PAPER SA",
    "figi_ticker": "ATC",
    "exchange_code": "PW",
    "security_type": "Common Stock",
    "market_sector": "Equity",
    "figi": "BBG000PMFXQ6",
    "source": "openfigi"
  },
  {
    "isin": "PLARLEN00012",
    "mbank_name": "ARLEN",
    "full_name": "ARLEN SA",
    "figi_ticker": "ARL",
    "exchange_code": "PW",
    "security_type": "Common Stock",
    "market_sector": "Equity",
    "figi": "BBG01VD0NZ11",
    "source": "openfigi"
  },
  {
    "isin": "CY1000031710",
    "mbank_name": "ASBIS",
    "full_name": "ASBISC ENTERPRISES PLC",
    "figi_ticker": "ASB",
    "exchange_code": "PW",
    "security_type": "Common Stock",
    "market_sector": "Equity",
    "figi": "BBG000TJWNB8",
    "source": "openfigi"
  },
  {
    "isin": "PLABS0000018",
    "mbank_name": "ASSECOBS",
    "full_name": "ASSECO BUSINESS SOLUTIONS SA",
    "figi_ticker": "ABS",
    "exchange_code": "PW",
    "security_type": "Common Stock",
    "market_sector": "Equity",
    "figi": "BBG000TGC1K4",
    "source": "openfigi"
  },
  {
    "isin": "PLSOFTB00016",
    "mbank_name": "ASSECOPOL",
    "full_name": "ASSECO POLAND SA",
    "figi_ticker": "ACP",
    "exchange_code": "PW",
    "security_type": "Common Stock",
    "market_sector": "Equity",
    "figi": "BBG000F6VHT6",
    "source": "openfigi"
  },
  {
    "isin": "PLASSEE00014",
    "mbank_name": "ASSECOSEE",
    "full_name": "ASSECO SOUTH EASTERN EUROPE",
    "figi_ticker": "ASE",
    "exchange_code": "PW",
    "security_type": "Common Stock",
    "market_sector": "Equity",
    "figi": "BBG000PRRCL3",
    "source": "openfigi"
  },
  {
    "isin": "PLATAL000046",
    "mbank_name": "ATAL",
    "full_name": "ATAL SA/POLAND",
    "figi_ticker": "1AT",
    "exchange_code": "PW",
    "security_type": "Common Stock",
    "market_sector": "Equity",
    "figi": "BBG0088LCR59",
    "source": "openfigi"
  },
  {
    "isin": "PLATREM00017",
    "mbank_name": "ATREM",
    "full_name": "ATREM SA",
    "figi_ticker": "ATR",
    "exchange_code": "PW",
    "security_type": "Common Stock",
    "market_sector": "Equity",
    "figi": "BBG000G8RFF5",
    "source": "openfigi"
  },
  {
    "isin": "PLATPRT00018",
    "mbank_name": "AUTOPARTN",
    "full_name": "AUTO PARTNER SA",
    "figi_ticker": "APR",
    "exchange_code": "PW",
    "security_type": "Common Stock",
    "market_sector": "Equity",
    "figi": "BBG00CVQSKH8",
    "source": "openfigi"
  },
  {
    "isin": "PLBNFTS00018",
    "mbank_name": "BENEFIT",
    "full_name": "BENEFIT SYSTEMS SA",
    "figi_ticker": "BFT",
    "exchange_code": "PW",
    "security_type": "Common Stock",
    "market_sector": "Equity",
    "figi": "BBG001N9TPG8",
    "source": "openfigi"
  },
  {
    "isin": "PLBLOBR00014",
    "mbank_name": "BLOOBER",
    "full_name": "BLOOBER TEAM SA",
    "figi_ticker": "BLO",
    "exchange_code": "PW",
    "security_type": "Common Stock",
    "market_sector": "Equity",
    "figi": "BBG001RWVSP4",
    "source": "openfigi"
  },
  {
    "isin": "PLBGZ0000010",
    "mbank_name": "BNPPPL",
    "full_name": "BNP PARIBAS BANK POLSKA SA",
    "figi_ticker": "BNPPPL",
    "exchange_code": "PW",
    "security_type": "Common Stock",
    "market_sector": "Equity",
    "figi": "BBG001DGK9X9",
    "source": "openfigi"
  },
  {
    "isin": "PLLWBGD00016",
    "mbank_name": "BOGDANKA",
    "full_name": "LUBELSKI WEGIEL BOGDANKA SA",
    "figi_ticker": "LWB",
    "exchange_code": "PW",
    "security_type": "Common Stock",
    "market_sector": "Equity",
    "figi": "BBG000G465N0",
    "source": "openfigi"
  },
  {
    "isin": "PLBRSZW00011",
    "mbank_name": "BORYSZEW",
    "full_name": "BORYSZEW SA",
    "figi_ticker": "BRS",
    "exchange_code": "PW",
    "security_type": "Common Stock",
    "market_sector": "Equity",
    "figi": "BBG000MH8133",
    "source": "openfigi"
  },
  {
    "isin": "PLBUDMX00013",
    "mbank_name": "BUDIMEX",
    "full_name": "BUDIMEX",
    "figi_ticker": "BDX",
    "exchange_code": "PW",
    "security_type": "Common Stock",
    "market_sector": "Equity",
    "figi": "BBG000MH51N4",
    "source": "openfigi"
  },
  {
    "isin": "PLCCC0000016",
    "mbank_name": "CCC",
    "full_name": "MODIVO SA",
    "figi_ticker": "MDV",
    "exchange_code": "PW",
    "security_type": "Common Stock",
    "market_sector": "Equity",
    "figi": "BBG000QLNJS7",
    "source": "openfigi"
  },
  {
    "isin": "PLOPTTC00011",
    "mbank_name": "CDPROJEKT",
    "full_name": "CD PROJEKT SA",
    "figi_ticker": "CDR",
    "exchange_code": "PW",
    "security_type": "Common Stock",
    "market_sector": "Equity",
    "figi": "BBG000D03WZ2",
    "source": "openfigi"
  },
  {
    "isin": "CZ0005112300",
    "mbank_name": "CEZ",
    "full_name": "CEZ AS",
    "figi_ticker": "CEZ",
    "exchange_code": "GR",
    "security_type": "Common Stock",
    "market_sector": "Equity",
    "figi": "BBG000BH4843",
    "source": "openfigi"
  },
  {
    "isin": "PLCTINT00018",
    "mbank_name": "CIGAMES",
    "full_name": "CIGAMES",
    "figi_ticker": "CIG",
    "exchange_code": "PW",
    "security_type": "Common Stock",
    "market_sector": "Equity",
    "figi": "BBG000RLFKZ4",
    "source": "openfigi"
  },
  {
    "isin": "PLCNTSL00014",
    "mbank_name": "COGNOR",
    "full_name": "COGNOR SA",
    "figi_ticker": "COG",
    "exchange_code": "PW",
    "security_type": "Common Stock",
    "market_sector": "Equity",
    "figi": "BBG000CJ1Z78",
    "source": "openfigi"
  },
  {
    "isin": "PLCMP0000017",
    "mbank_name": "COMP",
    "full_name": "COMP SA",
    "figi_ticker": "CMP",
    "exchange_code": "PW",
    "security_type": "Common Stock",
    "market_sector": "Equity",
    "figi": "BBG000Q74VR3",
    "source": "openfigi"
  },
  {
    "isin": "PLCRPJR00019",
    "mbank_name": "CREEPYJAR",
    "full_name": "CREEPY JAR SA",
    "figi_ticker": "CRJ",
    "exchange_code": "PW",
    "security_type": "Common Stock",
    "market_sector": "Equity",
    "figi": "BBG00LNBX3K8",
    "source": "openfigi"
  },
  {
    "isin": "PLR220000018",
    "mbank_name": "CYBERFLKS",
    "full_name": "CYBERFLKS SA",
    "figi_ticker": "CBF",
    "exchange_code": "PW",
    "security_type": "Common Stock",
    "market_sector": "Equity",
    "figi": "BBG00JDY67C4",
    "source": "openfigi"
  },
  {
    "isin": "PLCFRPT00013",
    "mbank_name": "CYFRPLSAT",
    "full_name": "CYFROWY POLSAT SA",
    "figi_ticker": "CPS",
    "exchange_code": "PW",
    "security_type": "Common Stock",
    "market_sector": "Equity",
    "figi": "BBG000R3K7R6",
    "source": "openfigi"
  },
  {
    "isin": "PLDADEL00013",
    "mbank_name": "DADELO",
    "full_name": "DADELO SA",
    "figi_ticker": "DAD",
    "exchange_code": "PW",
    "security_type": "Common Stock",
    "market_sector": "Equity",
    "figi": "BBG00YPZJVK9",
    "source": "openfigi"
  },
  {
    "isin": "PLPILAB00012",
    "mbank_name": "DATAWALK",
    "full_name": "DATAWALK SA",
    "figi_ticker": "DAT",
    "exchange_code": "PW",
    "security_type": "Common Stock",
    "market_sector": "Equity",
    "figi": "BBG00363T0R9",
    "source": "openfigi"
  },
  {
    "isin": "PLLCCRP00017",
    "mbank_name": "DEVELIA",
    "full_name": "DEVELIA SA",
    "figi_ticker": "DVL",
    "exchange_code": "PW",
    "security_type": "Common Stock",
    "market_sector": "Equity",
    "figi": "BBG000K04SV6",
    "source": "openfigi"
  },
  {
    "isin": "PLDGNST00012",
    "mbank_name": "DIAG",
    "full_name": "DIAGNOSTYKA SA-SERIES D/E/F",
    "figi_ticker": "DIA",
    "exchange_code": "PW",
    "security_type": "Common Stock",
    "market_sector": "Equity",
    "figi": "BBG01RQRT474",
    "source": "openfigi"
  },
  {
    "isin": "PLDINPL00011",
    "mbank_name": "DINOPL",
    "full_name": "DINO POLSKA SA",
    "figi_ticker": "DNP",
    "exchange_code": "PW",
    "security_type": "Common Stock",
    "market_sector": "Equity",
    "figi": "BBG00G59T6C1",
    "source": "openfigi"
  },
  {
    "isin": "PLDMDVL00012",
    "mbank_name": "DOMDEV",
    "full_name": "DOM DEVELOPMENT SA",
    "figi_ticker": "DOM",
    "exchange_code": "PW",
    "security_type": "Common Stock",
    "market_sector": "Equity",
    "figi": "BBG000G3XCV8",
    "source": "openfigi"
  },
  {
    "isin": "PLELEKT00016",
    "mbank_name": "ELEKTROTI",
    "full_name": "ELEKTROTIM SA",
    "figi_ticker": "ELT",
    "exchange_code": "PW",
    "security_type": "Common Stock",
    "market_sector": "Equity",
    "figi": "BBG000P3M4H4",
    "source": "openfigi"
  },
  {
    "isin": "PLENEA000013",
    "mbank_name": "ENEA",
    "full_name": "ENEA SA",
    "figi_ticker": "ENA",
    "exchange_code": "PW",
    "security_type": "Common Stock",
    "market_sector": "Equity",
    "figi": "BBG000VR0941",
    "source": "openfigi"
  },
  {
    "isin": "PLENERG00022",
    "mbank_name": "ENERGA",
    "full_name": "ENERGA SA",
    "figi_ticker": "ENG",
    "exchange_code": "PW",
    "security_type": "Common Stock",
    "market_sector": "Equity",
    "figi": "BBG00164NQJ9",
    "source": "openfigi"
  },
  {
    "isin": "PLENTER00017",
    "mbank_name": "ENTER",
    "full_name": "ENTER AIR SA",
    "figi_ticker": "ENT",
    "exchange_code": "PW",
    "security_type": "Common Stock",
    "market_sector": "Equity",
    "figi": "BBG009DVDX73",
    "source": "openfigi"
  },
  {
    "isin": "PLEURCH00011",
    "mbank_name": "EUROCASH",
    "full_name": "EUROCASH SA",
    "figi_ticker": "EUR",
    "exchange_code": "PW",
    "security_type": "Common Stock",
    "market_sector": "Equity",
    "figi": "BBG000PB9PB0",
    "source": "openfigi"
  },
  {
    "isin": "PLFERRO00016",
    "mbank_name": "FERRO",
    "full_name": "FERRO SA",
    "figi_ticker": "FRO",
    "exchange_code": "PW",
    "security_type": "Common Stock",
    "market_sector": "Equity",
    "figi": "BBG000QQXM71",
    "source": "openfigi"
  },
  {
    "isin": "PLGPW0000047",
    "mbank_name": "GPW",
    "full_name": "Gielda Papierów Wartosciowych w Warszawie S.A.",
    "figi_ticker": "GPW.WA",
    "exchange_code": "WSE",
    "security_type": "EQUITY",
    "market_sector": "Financial Services",
    "figi": "",
    "source": "yfinance",
    "yf_symbol": "GPW.WA"
  },
  {
    "isin": "PLZATRM00012",
    "mbank_name": "GRUPAAZOTY",
    "full_name": "GRUPA AZOTY SA",
    "figi_ticker": "ATT",
    "exchange_code": "PW",
    "security_type": "Common Stock",
    "market_sector": "Equity",
    "figi": "BBG000PR98K3",
    "source": "openfigi"
  },
  {
    "isin": "PLGRPRC00015",
    "mbank_name": "GRUPRACUJ",
    "full_name": "GRUPA PRACUJ SA",
    "figi_ticker": "GPP",
    "exchange_code": "PW",
    "security_type": "Common Stock",
    "market_sector": "Equity",
    "figi": "BBG013KVSYK4",
    "source": "openfigi"
  },
  {
    "isin": "PLBH00000012",
    "mbank_name": "HANDLOWY",
    "full_name": "BANK HANDLOWY W WARSZAWIE SA",
    "figi_ticker": "BHW",
    "exchange_code": "PW",
    "security_type": "Common Stock",
    "market_sector": "Equity",
    "figi": "BBG000CHZ7N9",
    "source": "openfigi"
  },
  {
    "isin": "US44853H1086",
    "mbank_name": "HUUUGE",
    "full_name": "HUUUGE INC",
    "figi_ticker": "HUG",
    "exchange_code": "PW",
    "security_type": "Common Stock",
    "market_sector": "Equity",
    "figi": "BBG00YYWMGX1",
    "source": "openfigi"
  },
  {
    "isin": "PLBSK0000017",
    "mbank_name": "INGBSK",
    "full_name": "ING BANK SLASKI SA",
    "figi_ticker": "ING",
    "exchange_code": "PW",
    "security_type": "Common Stock",
    "market_sector": "Equity",
    "figi": "BBG000DCV236",
    "source": "openfigi"
  },
  {
    "isin": "PLINTCS00010",
    "mbank_name": "INTERCARS",
    "full_name": "INTER CARS SA",
    "figi_ticker": "CAR",
    "exchange_code": "PW",
    "security_type": "Common Stock",
    "market_sector": "Equity",
    "figi": "BBG000PMF0R7",
    "source": "openfigi"
  },
  {
    "isin": "PLJSW0000015",
    "mbank_name": "JSW",
    "full_name": "JASTRZEBSKA SPOLKA WEGLOWA S",
    "figi_ticker": "JSW",
    "exchange_code": "PW",
    "security_type": "Common Stock",
    "market_sector": "Equity",
    "figi": "BBG000J20CG0",
    "source": "openfigi"
  },
  {
    "isin": "PLKETY000011",
    "mbank_name": "KETY",
    "full_name": "GRUPA KETY SA",
    "figi_ticker": "KTY",
    "exchange_code": "PW",
    "security_type": "Common Stock",
    "market_sector": "Equity",
    "figi": "BBG000MH5H77",
    "source": "openfigi"
  },
  {
    "isin": "PLKGHM000017",
    "mbank_name": "KGHM",
    "full_name": "KGHM POLSKA MIEDZ SA",
    "figi_ticker": "KGHPF",
    "exchange_code": "US",
    "security_type": "Common Stock",
    "market_sector": "Equity",
    "figi": "BBG000CD3YV5",
    "source": "openfigi"
  },
  {
    "isin": "PLKRK0000010",
    "mbank_name": "KRUK",
    "full_name": "KRUK SA",
    "figi_ticker": "KRU",
    "exchange_code": "PW",
    "security_type": "Common Stock",
    "market_sector": "Equity",
    "figi": "BBG001MGPLT2",
    "source": "openfigi"
  },
  {
    "isin": "PLLPP0000011",
    "mbank_name": "LPP",
    "full_name": "LPP SA",
    "figi_ticker": "LPP",
    "exchange_code": "PW",
    "security_type": "Common Stock",
    "market_sector": "Equity",
    "figi": "BBG000BNDZR5",
    "source": "openfigi"
  },
  {
    "isin": "PLLUBAW00013",
    "mbank_name": "LUBAWA",
    "full_name": "LUBAWA SA",
    "figi_ticker": "LBW",
    "exchange_code": "PW",
    "security_type": "Common Stock",
    "market_sector": "Equity",
    "figi": "BBG000CHZBK3",
    "source": "openfigi"
  },
  {
    "isin": "PLBRE0000012",
    "mbank_name": "MBANK",
    "full_name": "MBANK SA",
    "figi_ticker": "MBK",
    "exchange_code": "PW",
    "security_type": "Common Stock",
    "market_sector": "Equity",
    "figi": "BBG000DCTP92",
    "source": "openfigi"
  },
  {
    "isin": "PLBIG0000016",
    "mbank_name": "MILLENNIUM",
    "full_name": "BANK MILLENNIUM SA",
    "figi_ticker": "MIL",
    "exchange_code": "PW",
    "security_type": "Common Stock",
    "market_sector": "Equity",
    "figi": "BBG000DCTR89",
    "source": "openfigi"
  },
  {
    "isin": "PLMRBUD00015",
    "mbank_name": "MIRBUD",
    "full_name": "MIRBUD SA",
    "figi_ticker": "MRB",
    "exchange_code": "PW",
    "security_type": "Common Stock",
    "market_sector": "Equity",
    "figi": "BBG000RSFX27",
    "source": "openfigi"
  },
  {
    "isin": "PLMOBRK00013",
    "mbank_name": "MOBRUK",
    "full_name": "MO-BRUK J MOKRZYCKI LTD",
    "figi_ticker": "MBR",
    "exchange_code": "PW",
    "security_type": "Common Stock",
    "market_sector": "Equity",
    "figi": "BBG001D877Q4",
    "source": "openfigi"
  },
  {
    "isin": "HU0000153937",
    "mbank_name": "MOL",
    "full_name": "MOL HUNGARIAN OIL AND GAS PL",
    "figi_ticker": "MOL",
    "exchange_code": "HB",
    "security_type": "Common Stock",
    "market_sector": "Equity",
    "figi": "BBG000FZ5LX7",
    "source": "openfigi"
  },
  {
    "isin": "PLMURPL00190",
    "mbank_name": "MURAPOL",
    "full_name": "MURAPOL SA",
    "figi_ticker": "MUR",
    "exchange_code": "PW",
    "security_type": "Common Stock",
    "market_sector": "Equity",
    "figi": "BBG013P0KW01",
    "source": "openfigi"
  },
  {
    "isin": "PLTRFRM00018",
    "mbank_name": "NEUCA",
    "full_name": "NEUCA SA",
    "figi_ticker": "NEU",
    "exchange_code": "PW",
    "security_type": "Common Stock",
    "market_sector": "Equity",
    "figi": "BBG000Q4KL94",
    "source": "openfigi"
  },
  {
    "isin": "PLNEWAG00012",
    "mbank_name": "NEWAG",
    "full_name": "NEWAG SA",
    "figi_ticker": "NWG",
    "exchange_code": "PW",
    "security_type": "Common Stock",
    "market_sector": "Equity",
    "figi": "BBG005L9DRX5",
    "source": "openfigi"
  },
  {
    "isin": "PLTLKPL00017",
    "mbank_name": "ORANGEPL",
    "full_name": "ORANGE POLSKA SA",
    "figi_ticker": "OPL",
    "exchange_code": "PW",
    "security_type": "Common Stock",
    "market_sector": "Equity",
    "figi": "BBG000F6YJD6",
    "source": "openfigi"
  },
  {
    "isin": "PLPEKAO00016",
    "mbank_name": "PEKAO",
    "full_name": "BANK PEKAO SA",
    "figi_ticker": "PEO",
    "exchange_code": "PW",
    "security_type": "Common Stock",
    "market_sector": "Equity",
    "figi": "BBG000F714H9",
    "source": "openfigi"
  },
  {
    "isin": "NL0015000AU7",
    "mbank_name": "PEPCO",
    "full_name": "PEPCO GROUP NV",
    "figi_ticker": "PCO",
    "exchange_code": "PW",
    "security_type": "Common Stock",
    "market_sector": "Equity",
    "figi": "BBG010FN09V7",
    "source": "openfigi"
  },
  {
    "isin": "PLPGER000010",
    "mbank_name": "PGE",
    "full_name": "PGE SA",
    "figi_ticker": "PGE",
    "exchange_code": "PW",
    "security_type": "Common Stock",
    "market_sector": "Equity",
    "figi": "BBG000BP0PD1",
    "source": "openfigi"
  },
  {
    "isin": "PLPKN0000018",
    "mbank_name": "PKNORLEN",
    "full_name": "ORLEN SA",
    "figi_ticker": "PKN",
    "exchange_code": "PW",
    "security_type": "Common Stock",
    "market_sector": "Equity",
    "figi": "BBG000D0JDP8",
    "source": "openfigi"
  },
  {
    "isin": "PLPKO0000016",
    "mbank_name": "PKOBP",
    "full_name": "PKO BANK POLSKI SA",
    "figi_ticker": "PKO",
    "exchange_code": "PW",
    "security_type": "Common Stock",
    "market_sector": "Equity",
    "figi": "BBG000BMWXJ0",
    "source": "openfigi"
  },
  {
    "isin": "PLPKPCR00011",
    "mbank_name": "PKPCARGO",
    "full_name": "PKP CARGO SA",
    "figi_ticker": "PKP",
    "exchange_code": "PW",
    "security_type": "Common Stock",
    "market_sector": "Equity",
    "figi": "BBG0042Y52H6",
    "source": "openfigi"
  },
  {
    "isin": "PLPLAYW00015",
    "mbank_name": "PLAYWAY",
    "full_name": "PLAYWAY SA",
    "figi_ticker": "PLW",
    "exchange_code": "PW",
    "security_type": "Common Stock",
    "market_sector": "Equity",
    "figi": "BBG00DSX43F1",
    "source": "openfigi"
  },
  {
    "isin": "PLPZU0000011",
    "mbank_name": "PZU",
    "full_name": "POWSZECHNY ZAKLAD UBEZPIECZE",
    "figi_ticker": "PZU",
    "exchange_code": "PW",
    "security_type": "Common Stock",
    "market_sector": "Equity",
    "figi": "BBG000BTY1D9",
    "source": "openfigi"
  },
  {
    "isin": "PLQRCUS00012",
    "mbank_name": "QUERCUS",
    "full_name": "QUERCUS TFI SA",
    "figi_ticker": "QRS",
    "exchange_code": "PW",
    "security_type": "Common Stock",
    "market_sector": "Equity",
    "figi": "BBG000DKC505",
    "source": "openfigi"
  },
  {
    "isin": "PLRNBWT00031",
    "mbank_name": "RAINBOW",
    "full_name": "RAINBOW TOURS SA",
    "figi_ticker": "RBW",
    "exchange_code": "EU",
    "security_type": "Common Stock",
    "market_sector": "Equity",
    "figi": "BBG000THDL45",
    "source": "openfigi"
  },
  {
    "isin": "PLBZ00000044",
    "mbank_name": "SANPL",
    "full_name": "SANTANDER BANK POLSKA SA",
    "figi_ticker": "BKZHF",
    "exchange_code": "US",
    "security_type": "Common Stock",
    "market_sector": "Equity",
    "figi": "BBG000BJ9WF9",
    "source": "openfigi"
  },
  {
    "isin": "PLSLVCR00029",
    "mbank_name": "SELVITA",
    "full_name": "SELVITA CRO SA",
    "figi_ticker": "SLV",
    "exchange_code": "PW",
    "security_type": "Common Stock",
    "market_sector": "Equity",
    "figi": "BBG00QKSQVG4",
    "source": "openfigi"
  },
  {
    "isin": "PLSHPR000021",
    "mbank_name": "SHOPER",
    "full_name": "SHOPER SA",
    "figi_ticker": "SHO",
    "exchange_code": "PW",
    "security_type": "Common Stock",
    "market_sector": "Equity",
    "figi": "BBG011MS0Y69",
    "source": "openfigi"
  },
  {
    "isin": "PLSTLEX00019",
    "mbank_name": "STALEXP",
    "full_name": "STALEXPORT AUTOSTRADY SA",
    "figi_ticker": "STX",
    "exchange_code": "PW",
    "security_type": "Common Stock",
    "market_sector": "Equity",
    "figi": "BBG000MH22G3",
    "source": "openfigi"
  },
  {
    "isin": "PLCMPLD00016",
    "mbank_name": "SYGNITY",
    "full_name": "SYGNITY SA",
    "figi_ticker": "SGN",
    "exchange_code": "PW",
    "security_type": "Common Stock",
    "market_sector": "Equity",
    "figi": "BBG000MH5635",
    "source": "openfigi"
  },
  {
    "isin": "PLSNKTK00019",
    "mbank_name": "SYNEKTIK",
    "full_name": "SYNEKTIK SA",
    "figi_ticker": "SNT",
    "exchange_code": "PW",
    "security_type": "Common Stock",
    "market_sector": "Equity",
    "figi": "BBG001Y31JK8",
    "source": "openfigi"
  },
  {
    "isin": "PLTAURN00011",
    "mbank_name": "TAURONPE",
    "full_name": "TAURON POLSKA ENERGIA SA",
    "figi_ticker": "TPE",
    "exchange_code": "PW",
    "security_type": "Common Stock",
    "market_sector": "Equity",
    "figi": "BBG000RRSB32",
    "source": "openfigi"
  },
  {
    "isin": "PLLVTSF00010",
    "mbank_name": "TEXT",
    "full_name": "TEXT SA",
    "figi_ticker": "TXT",
    "exchange_code": "PW",
    "security_type": "Common Stock",
    "market_sector": "Equity",
    "figi": "BBG006B5TH67",
    "source": "openfigi"
  },
  {
    "isin": "PLTORPL00016",
    "mbank_name": "TORPOL",
    "full_name": "TORPOL SA",
    "figi_ticker": "TOR",
    "exchange_code": "PW",
    "security_type": "Common Stock",
    "market_sector": "Equity",
    "figi": "BBG006S735L2",
    "source": "openfigi"
  },
  {
    "isin": "PLTOYA000011",
    "mbank_name": "TOYA",
    "full_name": "TOYA SA",
    "figi_ticker": "TOA",
    "exchange_code": "PW",
    "security_type": "Common Stock",
    "market_sector": "Equity",
    "figi": "BBG001XQXFN8",
    "source": "openfigi"
  },
  {
    "isin": "PLTSQGM00016",
    "mbank_name": "TSGAMES",
    "full_name": "TEN SQUARE GAMES SA",
    "figi_ticker": "TEN",
    "exchange_code": "PW",
    "security_type": "Common Stock",
    "market_sector": "Equity",
    "figi": "BBG00KP793W1",
    "source": "openfigi"
  },
  {
    "isin": "PLUNMOT00013",
    "mbank_name": "UNIMOT",
    "full_name": "UNIMOT SA",
    "figi_ticker": "UNT",
    "exchange_code": "PW",
    "security_type": "Common Stock",
    "market_sector": "Equity",
    "figi": "BBG003CXJ5N0",
    "source": "openfigi"
  },
  {
    "isin": "PLVRCM000016",
    "mbank_name": "VERCOM",
    "full_name": "VERCOM SA- D",
    "figi_ticker": "VRC",
    "exchange_code": "PW",
    "security_type": "Common Stock",
    "market_sector": "Equity",
    "figi": "BBG0108LVM46",
    "source": "openfigi"
  },
  {
    "isin": "PLVOXEL00014",
    "mbank_name": "VOXEL",
    "full_name": "VOXEL SA",
    "figi_ticker": "VOX",
    "exchange_code": "PW",
    "security_type": "Common Stock",
    "market_sector": "Equity",
    "figi": "BBG0024QVW44",
    "source": "openfigi"
  },
  {
    "isin": "PLWRTPL00027",
    "mbank_name": "WIRTUALNA",
    "full_name": "WIRTUALNA POLSKA HOLDING SA",
    "figi_ticker": "WPL",
    "exchange_code": "PW",
    "security_type": "Common Stock",
    "market_sector": "Equity",
    "figi": "BBG008F7XFS0",
    "source": "openfigi"
  },
  {
    "isin": "PLWTCHN00030",
    "mbank_name": "WITTCHEN",
    "full_name": "WITTCHEN SA",
    "figi_ticker": "WTN",
    "exchange_code": "PW",
    "security_type": "Common Stock",
    "market_sector": "Equity",
    "figi": "BBG0020B44H9",
    "source": "openfigi"
  },
  {
    "isin": "PLXTRDM00011",
    "mbank_name": "XTB",
    "full_name": "X-TRADE BROKERS DOM MAKLERSK",
    "figi_ticker": "XTB",
    "exchange_code": "PW",
    "security_type": "Common Stock",
    "market_sector": "Equity",
    "figi": "BBG00CMM7YZ0",
    "source": "openfigi"
  },
  {
    "isin": "LU2910446546",
    "mbank_name": "ZABKA",
    "full_name": "ZABKA GROUP SA",
    "figi_ticker": "ZAB",
    "exchange_code": "PW",
    "security_type": "Common Stock",
    "market_sector": "Equity",
    "figi": "BBG01Q3NJQK7",
    "source": "openfigi"
  }
]